contractual/__init__.py
contractual/__version__.py
contractual-0.4.6.dist-info/METADATA
contractual-0.4.6.dist-info/WHEEL
contractual-0.4.6.dist-info/top_level.txt
contractual-0.4.6.dist-info/RECORD
