Metadata-Version: 2.1
Name: contractual
Version: 0.4.6
Summary: Contractual provides a method for verifying the function of mocks across modules and projects
Home-page: https://gitlab.com/pjbecotte/contractual
Author: Paul Becotte
Author-email: pjbecotte@gmail.com
License: UNKNOWN
Keywords: contract test pact verify
Platform: UNKNOWN
Classifier: Development Status :: 3 - Alpha
Classifier: Intended Audience :: Developers
Classifier: Topic :: Software Development :: Testing
Classifier: License :: OSI Approved :: MIT License
Classifier: Programming Language :: Python :: 3.7
Requires-Python: >=3.7, <4
